srgssr_publication_data_api/__init__.py
srgssr_publication_data_api/pdp_schema.py
srgssr_publication_data_api-0.4.4.dist-info/AUTHORS.rst
srgssr_publication_data_api-0.4.4.dist-info/LICENSE
srgssr_publication_data_api-0.4.4.dist-info/METADATA
srgssr_publication_data_api-0.4.4.dist-info/WHEEL
srgssr_publication_data_api-0.4.4.dist-info/top_level.txt
srgssr_publication_data_api-0.4.4.dist-info/RECORD
