Metadata-Version: 2.1
Name: srgssr-publication-data-api
Version: 0.4.4
Summary: Python client library to conveniently query the publication data of SRG/SSR
Home-page: https://github.com/SRGSSR/pdp_graphql_client_python
Author: SRGSSR PDP Team
Author-email: pdp@srgssr.ch
License: MIT license
Keywords: srgssr metadata pdp publication data
Platform: UNKNOWN
Classifier: Development Status :: 2 - Pre-Alpha
Classifier: Intended Audience :: Developers
Classifier: License :: OSI Approved :: MIT License
Classifier: Natural Language :: English
Classifier: Programming Language :: Python :: 3
Classifier: Programming Language :: Python :: 3.6
Classifier: Programming Language :: Python :: 3.7
Classifier: Programming Language :: Python :: 3.8
Requires-Dist: sgqlc
